aesop/__init__.py
aesop/aesop.py
aesop-0.0.1.dist-info/DESCRIPTION.rst
aesop-0.0.1.dist-info/METADATA
aesop-0.0.1.dist-info/RECORD
aesop-0.0.1.dist-info/WHEEL
aesop-0.0.1.dist-info/metadata.json
aesop-0.0.1.dist-info/top_level.txt
