Metadata-Version: 2.0
Name: aesop
Version: 0.0.1
Summary: Module for analyzing electrostatics with protein structures
Home-page: https://github.com/rohithmohan/aesop-python
Author: Reed Harrison, Rohith Mohan
Author-email: reed.harrison@email.ucr.edu, rohith.mohan@email.ucr.edu
License: GNU GENERAL PUBLIC LICENSE
